LICENSE
README
setup.py
django_ticker.egg-info/PKG-INFO
django_ticker.egg-info/SOURCES.txt
django_ticker.egg-info/dependency_links.txt
django_ticker.egg-info/not-zip-safe
django_ticker.egg-info/top_level.txt
ticker/__init__.py
ticker/admin.py
ticker/feeds.py
ticker/models.py
ticker/sitemaps.py
ticker/urls.py
ticker/views.py
ticker/widgets.py
ticker/templates/ticker/archive.html
ticker/templates/ticker/archive_by_tag.html
ticker/templates/ticker/details.html
ticker/templates/ticker/overview.html