Metadata-Version: 1.0
Name: django-ticker
Version: 0.2.1
Summary: A simple Django app for newsticker with a row level permission based workflow.
Home-page: http://github.com/jezdez/django-ticker/tree/master
Author: Jannis Leidel
Author-email: jannis@leidel.info
License: UNKNOWN
Platform: UNKNOWN
Classifier: Development Status :: 3 - Alpha
Classifier: Environment :: Web Environment
Classifier: Intended Audience :: Developers
Classifier: License :: OSI Approved :: BSD License
Classifier: Operating System :: OS Independent
Classifier: Programming Language :: Python
Classifier: Framework :: Django
